CMakeLists.txt
LICENSE
NOTICE
ai_optix-0.3.0.dist-info/METADATA
ai_optix-0.3.0.dist-info/WHEEL
ai_optix-0.3.0.dist-info/licenses/LICENSE
ai_optix-0.3.0.dist-info/licenses/NOTICE
ai_optix.libs/libgomp-a34b3233.so.1
ai_optix/__init__.py
ai_optix/_core.cpython-311-x86_64-linux-gnu.so
ai_optix/api/optimizer.py
ai_optix/api/profiler.py
ai_optix/benchmarks/__init__.py
ai_optix/benchmarks/benchmark_accuracy.py
ai_optix/benchmarks/benchmark_speed.py
ai_optix/benchmarks/mebs/__init__.py
ai_optix/benchmarks/mebs/batch_scaling.py
ai_optix/benchmarks/mebs/core_benchmark.py
ai_optix/benchmarks/mebs/device_manager.py
ai_optix/benchmarks/mebs/matmul_benchmark.py
ai_optix/benchmarks/mebs/mlp_benchmark.py
ai_optix/benchmarks/mebs/reporter.py
ai_optix/benchmarks/mebs/runner.py
ai_optix/benchmarks/mebs/timer.py
ai_optix/core/selector.py
ai_optix/detector/base.py
ai_optix/detector/dataloader.py
ai_optix/detector/gpu_idle.py
ai_optix/mebs/__init__.py
ai_optix/mebs/api.py
ai_optix/mebs/core/device.py
ai_optix/mebs/core/stats.py
ai_optix/mebs/core/timer.py
ai_optix/mebs/runners/base.py
ai_optix/mebs/runners/latency.py
ai_optix/mebs/runners/throughput.py
ai_optix/optix.py
ai_optix/profiler/cpu.py
ai_optix/profiler/gpu.py
ai_optix/profiler/metrics.py
ai_optix/reports/json_export.py
ai_optix/reports/markdown_report.py
src/cpp/kernels.cpp
ai_optix-0.3.0.dist-info/RECORD
