Metadata-Version: 2.4
Name: ai-optix
Version: 0.3.0
Classifier: License :: OSI Approved :: Apache Software License
Requires-Dist: typer>=0.9.0
Requires-Dist: rich>=13.0.0
Requires-Dist: psutil>=5.9.0
Requires-Dist: torch>=2.0.0
Requires-Dist: pydantic>=2.0.0
Requires-Dist: nvidia-ml-py>=12.535.133 ; sys_platform == 'linux'
Requires-Dist: numpy>=1.21.0
Requires-Dist: pytest>=7.0.0 ; extra == 'dev'
Requires-Dist: maturin>=1.0,<2.0 ; extra == 'dev'
Requires-Dist: patchelf>=0.17.0 ; extra == 'dev'
Provides-Extra: dev
License-File: LICENSE
License-File: NOTICE
Summary: High-performance AI optimization framework
Author-email: Vipin <ai.foundation.software@gmail.com>
License: Apache-2.0
Requires-Python: >=3.9
Project-URL: Homepage, https://github.com/Legend-Vipin/ai-optix
Project-URL: Source, https://github.com/Legend-Vipin/ai-optix
Project-URL: Issues, https://github.com/Legend-Vipin/ai-optix/issues
